ezfuse/__init__.py
ezfuse/cli.py
ezfuse-1.1.1.dist-info/entry_points.txt
ezfuse-1.1.1.dist-info/LICENSE
ezfuse-1.1.1.dist-info/WHEEL
ezfuse-1.1.1.dist-info/METADATA
ezfuse-1.1.1.dist-info/RECORD
