Metadata-Version: 2.1
Name: ezfuse
Version: 1.1.1
Summary: Quickly mount fuse filesystems in temporary directories
Home-page: https://github.com/essembeh/ezfuse
License: Apache-2.0
Author: Sébastien MB
Author-email: seb@essembeh.org
Requires-Python: >=3.8,<4.0
Classifier: Development Status :: 4 - Beta
Classifier: License :: OSI Approved :: Apache Software License
Classifier: Programming Language :: Python :: 3
Classifier: Programming Language :: Python :: 3.8
Classifier: Programming Language :: Python :: 3.9
Classifier: Programming Language :: Python :: 3.10
Classifier: Programming Language :: Python :: 3.11
Classifier: Topic :: Utilities
Requires-Dist: colorama (>=0.4.6,<0.5.0)
